weller/__init__.py
weller/dispather/__init__.py
weller/dispather/dispatcher/__init__.py
weller/dispather/dispatcher/weller.py
weller/dispather/storage/__init__.py
weller/dispather/storage/memory.py
weller/storage/__init__.py
weller/storage/memory/__init__.py
weller/storage/memory/base.py
weller/storage/memory/memory_storage.py
weller/storage/service/__init__.py
weller/storage/service/abstract.py
weller/storage/service/abstract_auto_cached.py
weller/types/__init__.py
weller/types/cache_data.py
weller/types/weller_service_data.py
weller-0.0.0a1.dist-info/LICENSE
weller-0.0.0a1.dist-info/METADATA
weller-0.0.0a1.dist-info/WHEEL
weller-0.0.0a1.dist-info/RECORD
