Metadata-Version: 2.1
Name: weller
Version: 0.0.0a1
Summary: Modern cache for modern people
Home-page: https://github.com/Sethis/weller
License: MIT
Author: Alexandr Bortnik
Author-email: sambonsttt@gmail.com
Requires-Python: >=3.9,<4.0
Classifier: Intended Audience :: Developers
Classifier: License :: OSI Approved :: MIT License
Classifier: Operating System :: OS Independent
Classifier: Programming Language :: Python :: 3
Classifier: Programming Language :: Python :: 3.9
Classifier: Programming Language :: Python :: 3.10
Classifier: Programming Language :: Python :: 3.11
Requires-Dist: fast-depends (==2.2.1)
Project-URL: Bug Tracker, https://github.com/Sethis/weller/issues
